README.rst
_description.org
lh-agpl3-LICENSE.txt
pyproject.toml
setup.py
bin/uxpProcessAgentOutcomes.py
bisos/__init__.py
bisos.gossonot.egg-info/PKG-INFO
bisos.gossonot.egg-info/SOURCES.txt
bisos.gossonot.egg-info/dependency_links.txt
bisos.gossonot.egg-info/not-zip-safe
bisos.gossonot.egg-info/requires.txt
bisos.gossonot.egg-info/top_level.txt
bisos/gossonot/__init__.py
bisos/gossonot/gossonotPkgThis.py