Metadata-Version: 2.2
Name: bisos.gossonot
Version: 0.12
Summary: bisos.gossonot: python scripts (Interactive Command Modules -- ICM) which provide GOSSONOT (Generalized Open-Source Self Organizing Network Of Things) facilities.
Author: Mohsen Banan
Author-email: libre@mohsen.1.banan.byname.net
Maintainer: Mohsen Banan
Maintainer-email: libre@mohsen.1.banan.byname.net
License: AGPL
Classifier: Development Status :: 5 - Production/Stable
Classifier: Intended Audience :: Developers
Classifier: License :: OSI Approved :: GNU Affero General Public License v3
Classifier: Operating System :: POSIX
Classifier: Programming Language :: Python
Classifier: Topic :: Software Development :: Libraries
Classifier: Topic :: Software Development :: Libraries :: Python Modules
Requires-Dist: bisos
Requires-Dist: bisos.b
Requires-Dist: bisos.common
Requires-Dist: bisos.csPlayer
Requires-Dist: bisos.things
Requires-Dist: setuptools==75.8.0
Dynamic: author
Dynamic: author-email
Dynamic: classifier
Dynamic: description
Dynamic: license
Dynamic: maintainer
Dynamic: maintainer-email
Dynamic: requires-dist
Dynamic: summary
